exit_codes/__init__.py
exit_codes/exit_code_error.py
exit_codes/exit_codes.py
exit_codes/version.py
exit_codes-1.3.0.dist-info/LICENSE
exit_codes-1.3.0.dist-info/METADATA
exit_codes-1.3.0.dist-info/WHEEL
exit_codes-1.3.0.dist-info/top_level.txt
exit_codes-1.3.0.dist-info/RECORD
