Metadata-Version: 2.1
Name: exit_codes
Version: 1.3.0
Summary: Platform-independent exit codes.
Home-page: http://github.com/sixty-north/exit-codes
Author: Sixty North AS
Author-email: austin@sixty-north.com
License: MIT
Platform: any
Classifier: Development Status :: 3 - Alpha
Classifier: Operating System :: OS Independent
Classifier: Programming Language :: Python
Provides-Extra: test
